responsibleai_text/__init__.py
responsibleai_text/version.py
responsibleai_text/common/__init__.py
responsibleai_text/common/constants.py
responsibleai_text/managers/__init__.py
responsibleai_text/managers/error_analysis_manager.py
responsibleai_text/managers/explainer_manager.py
responsibleai_text/rai_text_insights/__init__.py
responsibleai_text/rai_text_insights/rai_text_insights.py
responsibleai_text/utils/__init__.py
responsibleai_text/utils/feature_extractors.py
responsibleai_text/utils/question_answering.py
responsibleai_text/utils/genai_metrics/__init__.py
responsibleai_text/utils/genai_metrics/constants.py
responsibleai_text/utils/genai_metrics/metrics.py
responsibleai_text/utils/genai_metrics/scripts/__init__.py
responsibleai_text/utils/genai_metrics/scripts/_compute.py
responsibleai_text/utils/genai_metrics/scripts/coherence.py
responsibleai_text/utils/genai_metrics/scripts/equivalence.py
responsibleai_text/utils/genai_metrics/scripts/fluency.py
responsibleai_text/utils/genai_metrics/scripts/groundedness.py
responsibleai_text/utils/genai_metrics/scripts/relevance.py
responsibleai_text-0.2.7.dist-info/METADATA
responsibleai_text-0.2.7.dist-info/WHEEL
responsibleai_text-0.2.7.dist-info/top_level.txt
responsibleai_text-0.2.7.dist-info/RECORD
